README.md
setup.cfg
setup.py
Flask_Atomic.egg-info/PKG-INFO
Flask_Atomic.egg-info/SOURCES.txt
Flask_Atomic.egg-info/dependency_links.txt
Flask_Atomic.egg-info/requires.txt
Flask_Atomic.egg-info/top_level.txt
Flask_Atomic.egg-info/zip-safe
example/__init__.py
example/app.py
flask_atomic/__init__.py
flask_atomic/dao.py
flask_atomic/database.py
flask_atomic/db.py
flask_atomic/decorators.py
flask_atomic/ext.py
flask_atomic/helpers.py
flask_atomic/logger.py
flask_atomic/sqlalchemy.py
flask_atomic/auth/__init__.py
flask_atomic/auth/decorators.py
flask_atomic/auth/jwt.py
flask_atomic/builder/__init__.py
flask_atomic/builder/architect.py
flask_atomic/builder/cache.py
flask_atomic/builder/core.py
flask_atomic/builder/endpoints.py
flask_atomic/mixins/__init__.py
flask_atomic/mixins/columns.py
flask_atomic/mixins/core.py
flask_atomic/models/__init__.py
flask_atomic/models/basedao.py
flask_atomic/models/user.py
flask_atomic/orm/__init__.py
flask_atomic/orm/base.py
flask_atomic/orm/database.py
flask_atomic/orm/helpers.py
flask_atomic/orm/operators.py
flask_atomic/orm/serializer.py
flask_atomic/orm/utils.py
flask_atomic/orm/mixins/__init__.py
flask_atomic/orm/mixins/abstracts.py
flask_atomic/orm/mixins/columns.py
flask_atomic/orm/mixins/core.py
tests/__init__.py
tests/test_ext.py
tests/builder/__init__.py
tests/builder/test_architect.py
tests/builder/test_cache.py
tests/dao/__init__.py
tests/dao/test_base.py
tests/dao/test_data.py
tests/dao/test_query.py
tests/dao/buffer/__init__.py
tests/fixtures/__init__.py
tests/fixtures/fixtures.py
tests/orm/__init__.py
tests/orm/declaratives/__init__.py
tests/orm/declaratives/test_base.py
tests/orm/mixins/__init__.py
tests/orm/mixins/test_abstracts.py
tests/orm/mixins/test_columns.py
tests/orm/mixins/test_core.py